sort_natural_keys/__init__.py
sort_natural_keys-0.0.0.dist-info/METADATA
sort_natural_keys-0.0.0.dist-info/WHEEL
sort_natural_keys-0.0.0.dist-info/top_level.txt
sort_natural_keys-0.0.0.dist-info/RECORD
