Metadata-Version: 2.1
Name: sort-natural-keys
Version: 0.0.0
Summary: Sorts with natural keys an array of string.
Home-page: https://gitlab.com/quotengo/util/sort-natural-keys.git
Author: Jean-Sébastien Patenaude
Author-email: js.patenaude.quotengo@gmail.com
License: MIT
Platform: UNKNOWN
